django_pesapal/__init__.py
django_pesapal/conf.py
django_pesapal/models.py
django_pesapal/tests.py
django_pesapal/urls.py
django_pesapal/views.py
django_pesapal/migrations/0001_initial.py
django_pesapal/migrations/0002_transaction_payment_status.py
django_pesapal/migrations/0003_transaction_payment_method.py
django_pesapal/migrations/0004_auto_20150812_0051.py
django_pesapal/migrations/0005_auto_20160503_1036.py
django_pesapal/migrations/0006_auto_20241227_1046.py
django_pesapal/migrations/0007_transaction_payment_account.py
django_pesapal/migrations/__init__.py
django_pesapal/templates/django_pesapal/base.html
django_pesapal/templates/django_pesapal/post_payment.html
django_pesapalv3/__init__.py
django_pesapalv3/admin.py
django_pesapalv3/apps.py
django_pesapalv3/conf.py
django_pesapalv3/tests.py
django_pesapalv3/urls.py
django_pesapalv3/views.py
django_pesapalv3/migrations/__init__.py
django_pesapal-2.0.dist-info/AUTHORS.rst
django_pesapal-2.0.dist-info/LICENSE
django_pesapal-2.0.dist-info/METADATA
django_pesapal-2.0.dist-info/WHEEL
django_pesapal-2.0.dist-info/top_level.txt
django_pesapal-2.0.dist-info/RECORD
